tvsm_extractor/__init__.py
tvsm_extractor/run.py
tvsm_extractor-2.1.0.dist-info/METADATA
tvsm_extractor-2.1.0.dist-info/WHEEL
tvsm_extractor-2.1.0.dist-info/entry_points.txt
tvsm_extractor-2.1.0.dist-info/licenses/LICENSE
tvsm_extractor-2.1.0.dist-info/RECORD
