Metadata-Version: 2.3
Name: tvsm-extractor
Version: 2.1.0
Summary: Extract TVSM dataset
Project-URL: Homepage, https://github.com/tvquizphd/tvsm-extractor
Project-URL: Issues, https://github.com/tvquizphd/tvsm-extractor/issues
Author: John Hoffer
Classifier: License :: OSI Approved :: MIT License
Classifier: Operating System :: OS Independent
Requires-Python: >=3.10
Requires-Dist: librosa==0.10.2.post1
Requires-Dist: matplotlib==3.9.3
Requires-Dist: numpy==2.0.2
Requires-Dist: soundfile==0.12.1
